gamornet/__init__.py
gamornet/keras_module.py
gamornet/tflearn_module.py
gamornet-0.4.3.dist-info/LICENSE
gamornet-0.4.3.dist-info/METADATA
gamornet-0.4.3.dist-info/WHEEL
gamornet-0.4.3.dist-info/top_level.txt
gamornet-0.4.3.dist-info/RECORD
