Metadata-Version: 2.1
Name: gamornet
Version: 0.4.3
Summary: A CNN to classify galaxies morphologically
Home-page: http://gamornet.ghosharitra.com/
Author: Aritra Ghosh (http://ghosharitra.com)
Author-email: aritraghsh09@gmail.com
License: UNKNOWN
Project-URL: Source Code, https://github.com/aritraghsh09/GaMorNet
Project-URL: Documentation, https://gamornet.readthedocs.io/
Keywords: astrophysics astronomy galaxies convolutional neural networks morphological analysis morphology sdss candels
Platform: UNKNOWN
Classifier: Programming Language :: Python :: 3
Classifier: Development Status :: 5 - Production/Stable
Classifier: Environment :: GPU :: NVIDIA CUDA :: 10.1
Classifier: License :: OSI Approved :: GNU General Public License v3 (GPLv3)
Classifier: Intended Audience :: Science/Research
Classifier: Topic :: Scientific/Engineering :: Astronomy
Classifier: Topic :: Scientific/Engineering :: Physics
Requires-Python: ~=3.3
License-File: LICENSE
Requires-Dist: tensorflow-gpu (~=1.13)
Requires-Dist: tflearn (~=0.3)
Requires-Dist: keras (<2.4,~=2.2)
Requires-Dist: wget (~=3.2)
Requires-Dist: numpy (~=1.16)
Requires-Dist: progressbar2
Requires-Dist: h5py (<3.0.0)
